sphinx_contributor_listing/__init__.py
sphinx_contributor_listing/_version.py
sphinx_contributor_listing/callback.py
sphinx_contributor_listing/common.py
sphinx_contributor_listing/_static/contributors.css
sphinx_contributor_listing/_static/contributors.js
sphinx_contributor_listing-0.1.0.dist-info/licenses/LICENSE
sphinx_contributor_listing-0.1.0.dist-info/METADATA
sphinx_contributor_listing-0.1.0.dist-info/WHEEL
sphinx_contributor_listing-0.1.0.dist-info/top_level.txt
sphinx_contributor_listing-0.1.0.dist-info/RECORD
