Metadata-Version: 2.4
Name: sphinx-contributor-listing
Version: 0.1.0
Summary: A Sphinx extension for adding contributor listings to documentation pages.
License-Expression: GPL-3.0
Requires-Python: >=3.10
License-File: LICENSE
Requires-Dist: docutils>=0.21.2
Requires-Dist: sphinx~=7.0
Requires-Dist: GitPython
Dynamic: license-file
